flask_bcrypt.py
Flask_Bcrypt-1.0.0.dist-info/LICENSE
Flask_Bcrypt-1.0.0.dist-info/METADATA
Flask_Bcrypt-1.0.0.dist-info/WHEEL
Flask_Bcrypt-1.0.0.dist-info/top_level.txt
Flask_Bcrypt-1.0.0.dist-info/RECORD
